{"name":"Services","tagline":"Services for Ruby","body":"# Services\r\n\r\n[![Gem Version](https://badge.fury.io/rb/services.png)](http://badge.fury.io/rb/services)\r\n[![Build Status](https://secure.travis-ci.org/krautcomputing/services.png)](http://travis-ci.org/krautcomputing/services)\r\n[![Dependency Status](https://gemnasium.com/krautcomputing/services.png)](https://gemnasium.com/krautcomputing/services)\r\n[![Code Climate](https://codeclimate.com/github/krautcomputing/services.png)](https://codeclimate.com/github/krautcomputing/services)\r\n\r\nServices is a opinionated set of modules that can be used to implement the use cases (or services, contexts, whatchamacallit) of a Ruby application.\r\n\r\n## Requirements\r\n\r\nRuby >= 2.0\r\n\r\n## Installation\r\n\r\nAdd this line to your application's Gemfile:\r\n\r\n    gem 'services'\r\n\r\nAnd then execute:\r\n\r\n    $ bundle\r\n\r\nOr install it yourself as:\r\n\r\n    $ gem install services\r\n\r\n## Usage\r\n\r\nComing soon...\r\n\r\n## Contributing\r\n\r\n1. Fork it\r\n2. Create your feature branch (`git checkout -b my-new-feature`)\r\n3. Commit your changes (`git commit -am 'Add some feature'`)\r\n4. Push to the branch (`git push origin my-new-feature`)\r\n5. Create new Pull Request\r\n","google":"","note":"Don't delete this file! It's used internally to help with page regeneration."}